[
  {
    "name": "Green Gem",
    "sprite": 0,
    "trigger": {
      "description": "Whenever you take damage",
      "type": "take-damage"
    },
    "effect": {
      "description": "you gain 5 mana",
      "type": "gain-mana",
      "amount": "5"
    }
  },
  {
    "name": "Jade Elephant",
    "sprite": 1,
    "trigger": {
      "description": "When you don't move for 3 seconds",
      "type": "stand-still",
      "amount": "3"
    },
    "effect": {
      "description": "you gain 10 spellpower (+5/wave)",
      "type": "gain-spellpower",
      "amount": "10 wave 5 * +",
      "until": "move"
    }
  },
  {
    "name": "Golden Mask",
    "sprite": 2,
    "trigger": {
      "description": "When you take damage",
      "type": "take-damage"
    },
    "effect": {
      "description": "your next spell gains 100 additional spellpower.",
      "type": "gain-spellpower",
      "amount": "100",
      "until": "cast-spell"
    }
  },
  {
    "name": "Cursed Scroll",
    "sprite": 3,
    "trigger": {
      "description": "When you kill an enemy",
      "type": "on-kill"
    },
    "effect": {
      "description": "you gain 25 mana.",
      "type": "gain-mana",
      "amount": "25"
    }
  },
  {
    "name": "Life Link",
    "sprite": 6,
    "trigger": {
      "description": "When you deal damage",
      "type": "on-deal-damage"
    },
    "effect": {
      "description": "Heal 5 HP",
      "type": "heal",
      "amount": "5"
    }
  },
  {
    "name": "Swift Stone",
    "sprite": 7,
    "trigger": {
      "description": "When you cast a spell",
      "type": "cast-spell"
    },
    "effect": {
      "description": "Reduce next spell cooldown by 1s",
      "type": "reduce-cooldown",
      "amount": "1"
    }
  },
  {
    "name": "Rage Emblem",
    "sprite": 8,
    "trigger": {
      "description": "When you take damage",
      "type": "take-damage"
    },
    "effect": {
      "description": "Increase damage dealt by 20%",
      "type": "increase-damage",
      "amount": "20"
    }
  }
]